msys2_env/__main__.py
msys2_env/bash.ps1
msys2_env/fish.ps1
msys2_env/main.py
msys2_env/pack_install.ps1
msys2_env/pack_remove.ps1
msys2_env/shell_wrapper.py
msys2_env/wget.exe
msys2_env-2025.4.23.0.dist-info/METADATA
msys2_env-2025.4.23.0.dist-info/WHEEL
msys2_env-2025.4.23.0.dist-info/entry_points.txt
msys2_env-2025.4.23.0.dist-info/licenses/LICENSE
msys2_env-2025.4.23.0.dist-info/RECORD
