Metadata-Version: 2.4
Name: msys2-env
Version: 2025.4.23.0
Summary: Create Python virtual environment using MSYS2. (Windows only)
Project-URL: Repository, https://github.com/soda92/msys2_env
License-File: LICENSE
Requires-Python: >=3.10
